{
    "FIREFOX_AURORA": "",
    "FIREFOX_DEVEDITION": "68.0b8",
    "FIREFOX_ESR": "60.7.0esr",
    "FIREFOX_ESR_NEXT": "",
    "FIREFOX_NIGHTLY": "69.0a1",
    "LAST_MERGE_DATE": "2019-05-20",
    "LAST_RELEASE_DATE": "2019-05-21",
    "LAST_SOFTFREEZE_DATE": "2019-05-13",
    "LATEST_FIREFOX_DEVEL_VERSION": "68.0b8",
    "LATEST_FIREFOX_OLDER_VERSION": "3.6.28",
    "LATEST_FIREFOX_RELEASED_DEVEL_VERSION": "68.0b8",
    "LATEST_FIREFOX_VERSION": "67.0.1",
    "NEXT_MERGE_DATE": "2019-07-08",
    "NEXT_RELEASE_DATE": "2019-07-09",
    "NEXT_SOFTFREEZE_DATE": "2019-07-01"
}